apispec_starlette/__init__.py
apispec_starlette/_helpers.py
apispec_starlette/_plugin.py
apispec_starlette/_starlette.py
apispec_starlette/version.py
apispec_starlette-0.0.3.dist-info/LICENSE
apispec_starlette-0.0.3.dist-info/METADATA
apispec_starlette-0.0.3.dist-info/WHEEL
apispec_starlette-0.0.3.dist-info/top_level.txt
apispec_starlette-0.0.3.dist-info/RECORD
