Metadata-Version: 2.1
Name: apispec-starlette
Version: 0.0.3
Summary: APISpec plugin handling Starlette.
Home-page: https://colin-b.github.io/apispec_starlette/
Author: Colin Bounouar
Author-email: colin.bounouar.dev@gmail.com
Maintainer: Colin Bounouar
Maintainer-email: colin.bounouar.dev@gmail.com
License: MIT
Download-URL: https://pypi.org/project/apispec_starlette/
Project-URL: GitHub, https://github.com/Colin-b/apispec_starlette
Project-URL: Changelog, https://github.com/Colin-b/apispec_starlette/blob/master/CHANGELOG.md
Project-URL: Issues, https://github.com/Colin-b/apispec_starlette/issues
Keywords: starlette,apispec,openapi,swagger
Platform: Windows
Platform: Linux
Classifier: Development Status :: 5 - Production/Stable
Classifier: Intended Audience :: Developers
Classifier: License :: OSI Approved :: MIT License
Classifier: Natural Language :: English
Classifier: Programming Language :: Python
Classifier: Programming Language :: Python :: 3
Classifier: Programming Language :: Python :: 3.6
Classifier: Programming Language :: Python :: 3.7
Classifier: Programming Language :: Python :: 3.8
Classifier: Topic :: Software Development :: Build Tools
Requires-Python: >=3.6
Requires-Dist: starlette (==0.13.*)
Requires-Dist: apispec (<=4.*,>=3.3.*)
Requires-Dist: pyyaml (==5.*)
Provides-Extra: testing
Requires-Dist: requests (==2.*) ; extra == 'testing'
Requires-Dist: pytest-cov (==2.*) ; extra == 'testing'
